cf_xarray/__init__.py
cf_xarray/_version.py
cf_xarray/accessor.py
cf_xarray/coding.py
cf_xarray/criteria.py
cf_xarray/datasets.py
cf_xarray/formatting.py
cf_xarray/geometry.py
cf_xarray/groupers.py
cf_xarray/helpers.py
cf_xarray/options.py
cf_xarray/parametric.py
cf_xarray/py.typed
cf_xarray/sgrid.py
cf_xarray/units.py
cf_xarray/utils.py
cf_xarray/scripts/make_doc.py
cf_xarray/scripts/print_versions.py
cf_xarray-0.10.10.dist-info/licenses/LICENSE
cf_xarray-0.10.10.dist-info/METADATA
cf_xarray-0.10.10.dist-info/WHEEL
cf_xarray-0.10.10.dist-info/top_level.txt
cf_xarray-0.10.10.dist-info/RECORD
