Metadata-Version: 2.4
Name: cf_xarray
Version: 0.10.10
Summary: A convenience wrapper for using CF attributes on xarray objects
License:                                  Apache License
Project-URL: homepage, https://cf-xarray.readthedocs.io
Project-URL: documentation, https://cf-xarray.readthedocs.io
Project-URL: repository, https://github.com/xarray-contrib/cf-xarray.git
Project-URL: changelog, https://cf-xarray.readthedocs.io/en/latest/whats-new.html
Keywords: xarray,metadata,CF conventions
Classifier: Development Status :: 5 - Production/Stable
Classifier: License :: OSI Approved :: Apache Software License
Classifier: Natural Language :: English
Classifier: Operating System :: OS Independent
Classifier: Programming Language :: Python
Classifier: Programming Language :: Python :: 3.11
Classifier: Programming Language :: Python :: 3.12
Classifier: Programming Language :: Python :: 3.13
Requires-Python: >=3.11
License-File: LICENSE
Requires-Dist: xarray>=2024.7.0
Provides-Extra: all
Requires-Dist: matplotlib; extra == "all"
Requires-Dist: pint!=0.24.0,>=0.18; extra == "all"
Requires-Dist: shapely; extra == "all"
Requires-Dist: regex; extra == "all"
Requires-Dist: rich; extra == "all"
Requires-Dist: pooch; extra == "all"
Dynamic: license-file
